{
    "has_dir": {
        "doc/": false,
        "docs/": true,
        "examples/": false,
        "src/": false,
        "test/": false,
        "tests/": false
    },
    "has_file": {
        ".gitignore": true,
        "AUTHORS.md": false,
        "AUTHORS.rst": false,
        "CHANGELOG.md": false,
        "CHANGELOG.rst": false,
        "CONTRIBUTING.md": false,
        "CONTRIBUTING.rst": false,
        "LICENSE": true,
        "LICENSE.txt": false,
        "MANIFEST.in": true,
        "Makefile": false,
        "README": false,
        "README.md": false,
        "README.rst": true,
        "pytest.ini": false,
        "requirements.txt": false,
        "setup.cfg": true,
        "setup.py": true,
        "test-requirements.txt": false,
        "tox.ini": false
    },
    "license": "BSD-3-Clause",
    "lines_of_code": {
        "cfg": 15,
        "css": 1479,
        "html": 4707,
        "in": 13,
        "js": 37198,
        "json": 16375,
        "md": 99,
        "po": 199144,
        "py": 59374,
        "rst": 16480,
        "scss": 5045,
        "sh": 16,
        "svg": 705,
        "svgz": 5,
        "template": 20,
        "txt": 1060
    },
    "pep8_infringement": 4757,
    "shebang": {
        "#!/usr/bin/env python": 2
    }
}