{
    "has_dir": {
        "doc/": false,
        "docs/": false,
        "examples/": false,
        "src/": false,
        "test/": false,
        "tests/": false
    },
    "has_file": {
        ".gitignore": true,
        "AUTHORS.md": false,
        "AUTHORS.rst": false,
        "CHANGELOG.md": false,
        "CHANGELOG.rst": false,
        "CONTRIBUTING.md": false,
        "CONTRIBUTING.rst": false,
        "LICENSE": true,
        "LICENSE.txt": false,
        "MANIFEST.in": false,
        "Makefile": false,
        "README": false,
        "README.md": true,
        "README.rst": false,
        "pytest.ini": false,
        "requirements.txt": true,
        "setup.cfg": false,
        "setup.py": false,
        "test-requirements.txt": false,
        "tox.ini": false
    },
    "requirements": [
        "viivakoodi"
    ],
    "license": "AGPL-3.0",
    "lines_of_code": {
        "csv": 164,
        "md": 44,
        "po": 60096,
        "pot": 3352,
        "py": 9046,
        "rst": 1856,
        "sample": 12,
        "scenario": 218,
        "sh": 94,
        "svg": 36,
        "txt": 2,
        "xml": 3308,
        "yml": 22
    },
    "pep8_infringement": 55,
    "shebang": {
        "#!/usr/bin/env python": 2
    }
}