{
    "has_dir": {
        "doc/": false,
        "docs/": false,
        "examples/": false,
        "src/": false,
        "test/": false,
        "tests/": false
    },
    "has_file": {
        ".gitignore": true,
        "AUTHORS.md": false,
        "AUTHORS.rst": false,
        "CHANGELOG.md": false,
        "CHANGELOG.rst": false,
        "CONTRIBUTING.md": false,
        "CONTRIBUTING.rst": false,
        "LICENSE": true,
        "LICENSE.txt": false,
        "MANIFEST.in": true,
        "Makefile": false,
        "README": false,
        "README.md": true,
        "README.rst": false,
        "pytest.ini": false,
        "requirements.txt": true,
        "setup.cfg": false,
        "setup.py": true,
        "test-requirements.txt": false,
        "tox.ini": false
    },
    "requirements": [
        "cachetools>=2.0,<2.1",
        "decorator<4.1,>=4.0",
        "dogpile.cache>=0.6,<0.7",
        "jinja2>=2.8",
        "py3k-bcrypt==0.3",
        "pycrypto==2.6.1",
        "pytz",
        "pyyaml==3.12",
        "raven<6.0,>=5.9",
        "redis<2.11,>=2.10",
        "sqlalchemy<1.2,>=1.0",
        "tornado<5.0,>=4.0"
    ],
    "license": "MIT",
    "lines_of_code": {
        "in": 6,
        "md": 5,
        "py": 4300,
        "txt": 12
    },
    "pep8_infringement": 202,
    "shebang": {}
}