{
    "has_dir": {
        "doc/": false,
        "docs/": true,
        "examples/": false,
        "src/": false,
        "test/": false,
        "tests/": false
    },
    "has_file": {
        ".gitignore": true,
        "AUTHORS.md": false,
        "AUTHORS.rst": false,
        "CHANGELOG.md": false,
        "CHANGELOG.rst": false,
        "CONTRIBUTING.md": false,
        "CONTRIBUTING.rst": false,
        "LICENSE": false,
        "LICENSE.txt": true,
        "MANIFEST.in": true,
        "Makefile": false,
        "README": false,
        "README.md": true,
        "README.rst": true,
        "pytest.ini": false,
        "requirements.txt": false,
        "setup.cfg": true,
        "setup.py": true,
        "test-requirements.txt": false,
        "tox.ini": false
    },
    "license": "BSD-3-Clause",
    "lines_of_code": {
        "cfg": 2,
        "css": 393,
        "in": 7,
        "md": 206,
        "py": 2424,
        "rst": 1293,
        "sample": 640,
        "snakefile": 1854,
        "txt": 26,
        "yaml": 220
    },
    "pep8_infringement": 332,
    "requirements": [],
    "shebang": {
        "#!/usr/bin/env python3": 1
    }
}