{
    "has_dir": {
        "doc/": false,
        "docs/": false,
        "examples/": true,
        "src/": false,
        "test/": false,
        "tests/": false
    },
    "has_file": {
        ".gitignore": false,
        "AUTHORS.md": false,
        "AUTHORS.rst": false,
        "CHANGELOG.md": false,
        "CHANGELOG.rst": false,
        "CONTRIBUTING.md": false,
        "CONTRIBUTING.rst": false,
        "LICENSE": false,
        "LICENSE.txt": true,
        "MANIFEST.in": false,
        "Makefile": false,
        "README": false,
        "README.md": true,
        "README.rst": false,
        "pytest.ini": false,
        "requirements.txt": false,
        "setup.cfg": true,
        "setup.py": true,
        "test-requirements.txt": false,
        "tox.ini": false
    },
    "license": "MIT",
    "lines_of_code": {
        "cfg": 2,
        "md": 132,
        "py": 409,
        "txt": 21
    },
    "pep8_infringement": 11,
    "requirements": [
        "awscli",
        "boto",
        "boto3"
    ],
    "shebang": {
        "#!/usr/bin/env python": 7
    }
}