{
    "has_dir": {
        "doc/": true,
        "docs/": false,
        "examples/": false,
        "src/": false,
        "test/": false,
        "tests/": false
    },
    "has_file": {
        ".gitignore": true,
        "AUTHORS.md": false,
        "AUTHORS.rst": false,
        "CHANGELOG.md": false,
        "CHANGELOG.rst": false,
        "CONTRIBUTING.md": false,
        "CONTRIBUTING.rst": false,
        "LICENSE": false,
        "LICENSE.txt": true,
        "MANIFEST.in": false,
        "Makefile": false,
        "README": false,
        "README.md": true,
        "README.rst": false,
        "pytest.ini": false,
        "requirements.txt": false,
        "setup.cfg": false,
        "setup.py": true,
        "test-requirements.txt": false,
        "tox.ini": true
    },
    "license": "MIT",
    "lines_of_code": {
        "": 21,
        "cfg": 9,
        "ini": 22,
        "j2": 5,
        "md": 396,
        "py": 1205,
        "sample": 640,
        "svg": 149,
        "txt": 18,
        "yml": 360
    },
    "pep8_infringement": 0,
    "requirements": [
        "six",
        "tldextract>=2.0.1"
    ],
    "shebang": {
        "#!/usr/bin/env python": 1
    }
}