{
    "has_dir": {
        "doc/": false,
        "docs/": false,
        "examples/": true,
        "src/": false,
        "test/": false,
        "tests/": false
    },
    "has_file": {
        ".gitignore": true,
        "AUTHORS.md": false,
        "AUTHORS.rst": false,
        "CHANGELOG.md": false,
        "CHANGELOG.rst": false,
        "CONTRIBUTING.md": false,
        "CONTRIBUTING.rst": false,
        "LICENSE": true,
        "LICENSE.txt": false,
        "MANIFEST.in": false,
        "Makefile": false,
        "README": false,
        "README.md": true,
        "README.rst": false,
        "pytest.ini": false,
        "requirements.txt": true,
        "setup.cfg": false,
        "setup.py": true,
        "test-requirements.txt": false,
        "tox.ini": true
    },
    "license": "MIT",
    "lines_of_code": {
        "ini": 56,
        "md": 104,
        "py": 440,
        "sh": 7,
        "txt": 26
    },
    "pep8_infringement": 101,
    "requirements": [
        "aiofiles>=0.3.1",
        "appdirs>=1.4.3",
        "httptools>=0.0.9",
        "packaging>=16.8",
        "pika>=0.10.0",
        "sanic>=0.5.1",
        "six>=1.10.0",
        "ujson>=1.35",
        "uvloop>=0.8.0",
        "websockets>=3.3"
    ],
    "shebang": {}
}