{
    "has_dir": {
        "doc/": false,
        "docs/": true,
        "examples/": false,
        "src/": false,
        "test/": false,
        "tests/": true
    },
    "has_file": {
        ".gitignore": true,
        "AUTHORS.md": false,
        "AUTHORS.rst": false,
        "CHANGELOG.md": false,
        "CHANGELOG.rst": false,
        "CONTRIBUTING.md": false,
        "CONTRIBUTING.rst": false,
        "LICENSE": true,
        "LICENSE.txt": false,
        "MANIFEST.in": false,
        "Makefile": true,
        "README": false,
        "README.md": true,
        "README.rst": true,
        "pytest.ini": false,
        "requirements.txt": true,
        "setup.cfg": false,
        "setup.py": true,
        "test-requirements.txt": false,
        "tox.ini": false
    },
    "license": "Unlicense",
    "lines_of_code": {
        "centos7": 81,
        "css": 276,
        "html": 41,
        "ini": 0,
        "js": 44,
        "md": 322,
        "py": 7841,
        "rst": 46,
        "sample": 16,
        "svg": 40,
        "txt": 37
    }
}