{
    "has_dir": {
        "doc/": true,
        "docs/": false,
        "examples/": false,
        "src/": false,
        "test/": false,
        "tests/": false
    },
    "has_file": {
        ".gitignore": true,
        "AUTHORS.md": false,
        "AUTHORS.rst": false,
        "CHANGELOG.md": false,
        "CHANGELOG.rst": false,
        "CONTRIBUTING.md": false,
        "CONTRIBUTING.rst": false,
        "LICENSE": true,
        "LICENSE.txt": false,
        "MANIFEST.in": true,
        "Makefile": false,
        "README": false,
        "README.md": true,
        "README.rst": false,
        "pytest.ini": false,
        "requirements.txt": false,
        "setup.cfg": false,
        "setup.py": true,
        "test-requirements.txt": false,
        "tox.ini": false
    },
    "license": "CC-BY-NC-3.0",
    "lines_of_code": {
        "csv": 147,
        "html": 46,
        "in": 11,
        "js": 1168,
        "md": 63,
        "py": 5746,
        "rst": 1007,
        "svg": 3271,
        "txt": 57
    },
    "pep8_infringement": 282,
    "requirements": [
        "numpy",
        "orange3",
        "pandas",
        "scipy>=0.17",
        "statsmodels>=0.6.1"
    ],
    "shebang": {
        "#!/usr/bin/env python": 1,
        "#!/usr/bin/env python3": 1
    }
}