{
    "has_dir": {
        "doc/": true,
        "docs/": false,
        "examples/": false,
        "src/": false,
        "test/": false,
        "tests/": false
    },
    "has_file": {
        ".gitignore": true,
        "AUTHORS.md": false,
        "AUTHORS.rst": false,
        "CHANGELOG.md": false,
        "CHANGELOG.rst": false,
        "CONTRIBUTING.md": false,
        "CONTRIBUTING.rst": true,
        "LICENSE": true,
        "LICENSE.txt": false,
        "MANIFEST.in": true,
        "Makefile": false,
        "README": false,
        "README.md": false,
        "README.rst": true,
        "pytest.ini": false,
        "requirements.txt": true,
        "setup.cfg": true,
        "setup.py": true,
        "test-requirements.txt": true,
        "tox.ini": true
    },
    "license": "Apache-2.0",
    "lines_of_code": {
        "cfg": 61,
        "conf": 76,
        "in": 6,
        "ini": 97,
        "json": 2,
        "mako": 22,
        "py": 11566,
        "rst": 87,
        "sql": 213,
        "txt": 46,
        "wsgi": 36
    },
    "pep8_infringement": 9,
    "requirements": [
        "autobahn>=0.10.1",
        "eventlet!=0.18.3,>=0.18.2",
        "keystonemiddleware!=4.5.0,>=4.2.0",
        "oslo.concurrency>=3.8.0",
        "oslo.config>=3.14.0,!=3.18.0",
        "oslo.db!=4.13.2,>=4.11.0,!=4.13.1",
        "oslo.log>=3.11.0",
        "oslo.messaging>=5.2.0",
        "oslo.policy>=1.15.0",
        "oslosphinx!=3.4.0,>=2.5.0",
        "pbr>=1.6",
        "pecan!=1.2,!=1.0.4,!=1.0.2,>=1.0.0,!=1.0.3",
        "wsme>=0.8"
    ],
    "shebang": {
        "#!/usr/bin/env python": 2
    }
}