{
    "has_dir": {
        "doc/": true,
        "docs/": false,
        "examples/": false,
        "src/": false,
        "test/": false,
        "tests/": false
    },
    "has_file": {
        ".gitignore": true,
        "AUTHORS.md": false,
        "AUTHORS.rst": false,
        "CHANGELOG.md": false,
        "CHANGELOG.rst": false,
        "CONTRIBUTING.md": false,
        "CONTRIBUTING.rst": false,
        "LICENSE": true,
        "LICENSE.txt": false,
        "MANIFEST.in": false,
        "Makefile": false,
        "README": false,
        "README.md": false,
        "README.rst": false,
        "pytest.ini": false,
        "requirements.txt": false,
        "setup.cfg": false,
        "setup.py": false,
        "test-requirements.txt": false,
        "tox.ini": false
    },
    "license": "AGPL-3.0",
    "lines_of_code": {
        "conf": 67,
        "config": 662,
        "css": 5369,
        "dist": 424,
        "html": 23378,
        "js": 18672,
        "json": 12132,
        "markdown": 3059,
        "md": 4941,
        "mdown": 254,
        "mod": 38,
        "pl": 11115,
        "pm": 51521,
        "properties": 13,
        "psgi": 8,
        "py": 9180,
        "rss": 1171,
        "sh": 3249,
        "snapshot": 8347,
        "sql": 22180,
        "t": 16022,
        "tt2": 6172,
        "txt": 210152,
        "vm": 3684,
        "xml": 10045,
        "xsl": 2016,
        "yml": 974
    },
    "pep8_infringement": 1143,
    "requirements": [],
    "shebang": {
        "#!/usr/bin/env python3": 11
    }
}