{
    "has_dir": {
        "doc/": false,
        "docs/": true,
        "examples/": false,
        "src/": false,
        "test/": false,
        "tests/": false
    },
    "has_file": {
        ".gitignore": true,
        "AUTHORS.md": false,
        "AUTHORS.rst": false,
        "CHANGELOG.md": false,
        "CHANGELOG.rst": false,
        "CONTRIBUTING.md": false,
        "CONTRIBUTING.rst": false,
        "LICENSE": true,
        "LICENSE.txt": false,
        "MANIFEST.in": true,
        "Makefile": false,
        "README": false,
        "README.md": true,
        "README.rst": false,
        "pytest.ini": false,
        "requirements.txt": true,
        "setup.cfg": true,
        "setup.py": true,
        "test-requirements.txt": true,
        "tox.ini": true
    },
    "license": "MIT",
    "lines_of_code": {
        "cfg": 2,
        "html": 228,
        "in": 3,
        "ini": 19,
        "ipynb": 585,
        "js": 135,
        "json": 1288,
        "md": 137,
        "py": 4277,
        "rst": 193,
        "svg": 18,
        "txt": 18,
        "yaml": 71
    },
    "pep8_infringement": 99,
    "shebang": {}
}