{
    "has_dir": {
        "doc/": false,
        "docs/": false,
        "examples/": false,
        "src/": false,
        "test/": false,
        "tests/": true
    },
    "has_file": {
        ".gitignore": true,
        "AUTHORS.md": false,
        "AUTHORS.rst": false,
        "CHANGELOG.md": false,
        "CHANGELOG.rst": false,
        "CONTRIBUTING.md": false,
        "CONTRIBUTING.rst": true,
        "LICENSE": true,
        "LICENSE.txt": false,
        "MANIFEST.in": true,
        "Makefile": false,
        "README": false,
        "README.md": false,
        "README.rst": true,
        "pytest.ini": false,
        "requirements.txt": true,
        "setup.cfg": true,
        "setup.py": true,
        "test-requirements.txt": false,
        "tox.ini": true
    },
    "license": "ISC",
    "lines_of_code": {
        "": 44,
        "cfg": 26,
        "html": 168,
        "in": 10,
        "ini": 18,
        "md": 15,
        "py": 392,
        "rst": 169,
        "sample": 640,
        "txt": 15
    },
    "pep8_infringement": 0,
    "requirements": [
        "markupsafe"
    ],
    "shebang": {
        "#!/usr/bin/env python": 1
    }
}