{
    "has_dir": {
        "doc/": false,
        "docs/": false,
        "examples/": false,
        "src/": true,
        "test/": false,
        "tests/": true
    },
    "has_file": {
        ".gitignore": true,
        "AUTHORS.md": false,
        "AUTHORS.rst": false,
        "CHANGELOG.md": false,
        "CHANGELOG.rst": false,
        "CONTRIBUTING.md": false,
        "CONTRIBUTING.rst": false,
        "LICENSE": true,
        "LICENSE.txt": false,
        "MANIFEST.in": false,
        "Makefile": false,
        "README": false,
        "README.md": true,
        "README.rst": false,
        "pytest.ini": false,
        "requirements.txt": true,
        "setup.cfg": false,
        "setup.py": true,
        "test-requirements.txt": false,
        "tox.ini": false
    },
    "license": "MIT",
    "lines_of_code": {
        "csv": 59415,
        "md": 17,
        "py": 3908,
        "txt": 3
    },
    "pep8_infringement": 1640,
    "requirements": [
        "future==0.16.0",
        "timeout-decorator==0.3.3",
        "wheel==0.24.0"
    ],
    "shebang": {}
}