{
    "has_dir": {
        "doc/": false,
        "docs/": false,
        "examples/": false,
        "src/": false,
        "test/": false,
        "tests/": false
    },
    "has_file": {
        ".gitignore": true,
        "AUTHORS.md": false,
        "AUTHORS.rst": false,
        "CHANGELOG.md": false,
        "CHANGELOG.rst": false,
        "CONTRIBUTING.md": false,
        "CONTRIBUTING.rst": false,
        "LICENSE": false,
        "LICENSE.txt": true,
        "MANIFEST.in": true,
        "Makefile": true,
        "README": false,
        "README.md": true,
        "README.rst": false,
        "pytest.ini": false,
        "requirements.txt": false,
        "setup.cfg": true,
        "setup.py": true,
        "test-requirements.txt": false,
        "tox.ini": false
    },
    "license": "MIT",
    "lines_of_code": {
        "cfg": 2,
        "go": 6319,
        "in": 2,
        "lock": 138,
        "md": 162,
        "proto": 94,
        "py": 1328,
        "sh": 74,
        "txt": 22,
        "yaml": 41,
        "yml": 76
    },
    "pep8_infringement": 280,
    "requirements": [
        "grpcio",
        "protobuf"
    ],
    "shebang": {}
}