{
    "has_dir": {
        "doc/": false,
        "docs/": true,
        "examples/": false,
        "src/": false,
        "test/": false,
        "tests/": true
    },
    "has_file": {
        ".gitignore": true,
        "AUTHORS.md": false,
        "AUTHORS.rst": false,
        "CHANGELOG.md": false,
        "CHANGELOG.rst": false,
        "CONTRIBUTING.md": true,
        "CONTRIBUTING.rst": false,
        "LICENSE": true,
        "LICENSE.txt": false,
        "MANIFEST.in": true,
        "Makefile": true,
        "README": false,
        "README.md": true,
        "README.rst": false,
        "pytest.ini": true,
        "requirements.txt": false,
        "setup.cfg": false,
        "setup.py": true,
        "test-requirements.txt": false,
        "tox.ini": true
    },
    "license": "MIT",
    "lines_of_code": {
        "bak": 0,
        "in": 9,
        "ini": 32,
        "json": 1000,
        "md": 55,
        "py": 10675,
        "rst": 2993,
        "sh": 16,
        "sol": 288,
        "txt": 28
    },
    "pep8_infringement": 373,
    "requirements": [
        "anyconfig>=0.7.0",
        "click>=6.6",
        "contextlib2>=0.5.4",
        "eth-testrpc>=1.1.0",
        "ethereum-utils>=0.2.0",
        "jsonschema>=2.5.1",
        "py-geth>=1.8.0",
        "py-solc>=1.0.0",
        "pylru>=1.0.9",
        "pysha3>1.0.0,>=0.3,!=1.0",
        "pytest>=2.7.2",
        "toposort>=1.4",
        "watchdog>=0.8.3",
        "web3>=3.7.1"
    ],
    "shebang": {
        "#!/usr/bin/env python": 1
    }
}