{
    "has_dir": {
        "doc/": false,
        "docs/": true,
        "examples/": true,
        "src/": false,
        "test/": false,
        "tests/": true
    },
    "has_file": {
        ".gitignore": true,
        "AUTHORS.md": false,
        "AUTHORS.rst": true,
        "CHANGELOG.md": false,
        "CHANGELOG.rst": false,
        "CONTRIBUTING.md": false,
        "CONTRIBUTING.rst": false,
        "LICENSE": true,
        "LICENSE.txt": false,
        "MANIFEST.in": true,
        "Makefile": false,
        "README": false,
        "README.md": false,
        "README.rst": true,
        "pytest.ini": false,
        "requirements.txt": false,
        "setup.cfg": true,
        "setup.py": true,
        "test-requirements.txt": false,
        "tox.ini": false
    },
    "license": "LGPL-2.1",
    "lines_of_code": {
        "000": 100443,
        "EDF": 5714,
        "SVP": 82,
        "TXT": 831,
        "abs": 1152,
        "asc": 4985,
        "asvp": 122,
        "bat": 242,
        "calc": 26,
        "cfg": 6,
        "cnv": 99204,
        "conf": 5,
        "css_t": 402,
        "csv": 55769,
        "d14": 69,
        "d15": 68,
        "d16": 67,
        "d17": 65,
        "d18": 78,
        "d19": 72,
        "d20": 69,
        "d21": 73,
        "d25": 40,
        "d26": 56,
        "d27": 73,
        "d28": 65,
        "d29": 47,
        "d30": 70,
        "d31": 54,
        "d32": 55,
        "d33": 50,
        "d34": 53,
        "edf": 1695,
        "html": 33,
        "in": 2,
        "ini": 3245,
        "json": 10,
        "m": 37,
        "m1": 3834,
        "pro": 3582,
        "psa": 317,
        "py": 39673,
        "pyx": 179,
        "pyxbld": 10,
        "raw": 3698,
        "rst": 2894,
        "s12": 428,
        "sample": 640,
        "spec": 224,
        "ssp": 721,
        "stylesheet": 1330,
        "sv1": 1732,
        "sva": 3572,
        "svp": 7505,
        "temp": 35,
        "tsv": 52,
        "txt": 5182,
        "unb": 2827,
        "v14": 63,
        "v15": 62,
        "v16": 61,
        "v17": 59,
        "v18": 72,
        "v19": 66,
        "v20": 63,
        "v21": 67,
        "yml": 118
    },
    "pep8_infringement": 3796,
    "requirements": [],
    "shebang": {
        "#!/usr/bin/env python": 1
    }
}