{
    "has_dir": {
        "doc/": false,
        "docs/": true,
        "examples/": true,
        "src/": false,
        "test/": false,
        "tests/": true
    },
    "has_file": {
        ".gitignore": false,
        "AUTHORS.md": false,
        "AUTHORS.rst": false,
        "CHANGELOG.md": false,
        "CHANGELOG.rst": false,
        "CONTRIBUTING.md": false,
        "CONTRIBUTING.rst": false,
        "LICENSE": true,
        "LICENSE.txt": false,
        "MANIFEST.in": true,
        "Makefile": false,
        "README": true,
        "README.md": false,
        "README.rst": true,
        "pytest.ini": false,
        "requirements.txt": false,
        "setup.cfg": false,
        "setup.py": true,
        "test-requirements.txt": false,
        "tox.ini": false
    },
    "license": "EPL-1.0",
    "lines_of_code": {
        "conf": 4,
        "css_t": 28,
        "html": 27,
        "in": 2,
        "py": 11620,
        "rst": 1571,
        "sample": 640
    },
    "pep8_infringement": 569,
    "requirements": [
        "crypto>=2.6"
    ],
    "shebang": {
        "#!/usr/bin/env python3": 1,
        "#!/usr/bin/env python3.4": 26
    }
}