{
    "has_dir": {
        "doc/": false,
        "docs/": false,
        "examples/": false,
        "src/": false,
        "test/": false,
        "tests/": false
    },
    "has_file": {
        ".gitignore": true,
        "AUTHORS.md": false,
        "AUTHORS.rst": false,
        "CHANGELOG.md": false,
        "CHANGELOG.rst": false,
        "CONTRIBUTING.md": false,
        "CONTRIBUTING.rst": false,
        "LICENSE": false,
        "LICENSE.txt": true,
        "MANIFEST.in": false,
        "Makefile": false,
        "README": false,
        "README.md": true,
        "README.rst": false,
        "pytest.ini": false,
        "requirements.txt": true,
        "setup.cfg": false,
        "setup.py": true,
        "test-requirements.txt": false,
        "tox.ini": false
    },
    "license": "Unlicense",
    "lines_of_code": {
        "md": 21,
        "py": 243,
        "sample": 640,
        "txt": 27
    },
    "pep8_infringement": 6,
    "requirements": [
        "jsonrpclib-pelix",
        "pybitcoin>=0.9.10",
        "pyyaml"
    ],
    "shebang": {
        "#!/usr/bin/env python": 1
    }
}