{
    "has_dir": {
        "doc/": false,
        "docs/": true,
        "examples/": false,
        "src/": false,
        "test/": false,
        "tests/": false
    },
    "has_file": {
        ".gitignore": true,
        "AUTHORS.md": false,
        "AUTHORS.rst": false,
        "CHANGELOG.md": false,
        "CHANGELOG.rst": false,
        "CONTRIBUTING.md": false,
        "CONTRIBUTING.rst": false,
        "LICENSE": true,
        "LICENSE.txt": false,
        "MANIFEST.in": true,
        "Makefile": false,
        "README": false,
        "README.md": true,
        "README.rst": false,
        "pytest.ini": false,
        "requirements.txt": false,
        "setup.cfg": false,
        "setup.py": true,
        "test-requirements.txt": false,
        "tox.ini": false
    },
    "license": "BSD-3-Clause",
    "lines_of_code": {
        "bat": 242,
        "in": 1,
        "md": 139,
        "py": 2188,
        "rst": 85,
        "sample": 640,
        "txt": 5,
        "yml": 21
    },
    "pep8_infringement": 136,
    "requirements": [
        "httpsig==1.1.2",
        "pyjwt==1.3.0",
        "requests>=2.3.0",
        "six>=1.8.0"
    ],
    "shebang": {
        "#!/usr/bin/env python": 1
    }
}