{
    "has_dir": {
        "doc/": false,
        "docs/": false,
        "examples/": true,
        "src/": false,
        "test/": false,
        "tests/": false
    },
    "has_file": {
        ".gitignore": true,
        "AUTHORS.md": false,
        "AUTHORS.rst": false,
        "CHANGELOG.md": false,
        "CHANGELOG.rst": false,
        "CONTRIBUTING.md": false,
        "CONTRIBUTING.rst": false,
        "LICENSE": false,
        "LICENSE.txt": true,
        "MANIFEST.in": true,
        "Makefile": true,
        "README": false,
        "README.md": true,
        "README.rst": false,
        "pytest.ini": false,
        "requirements.txt": true,
        "setup.cfg": true,
        "setup.py": true,
        "test-requirements.txt": false,
        "tox.ini": false
    },
    "license": "BSD-4-Clause",
    "lines_of_code": {
        "": 4,
        "cfg": 11,
        "cpp": 1234,
        "h": 370,
        "in": 4,
        "ipynb": 1160,
        "m": 83,
        "md": 69,
        "py": 2281,
        "pyx": 27,
        "sample": 640,
        "txt": 56,
        "yml": 14
    },
    "pep8_infringement": 15,
    "requirements": [
        "cython>=0.19.1",
        "numpy>=1.7.1",
        "scipy>=0.12.0"
    ],
    "shebang": {}
}