{
    "has_dir": {
        "doc/": false,
        "docs/": true,
        "examples/": true,
        "src/": false,
        "test/": false,
        "tests/": true
    },
    "has_file": {
        ".gitignore": true,
        "AUTHORS.md": false,
        "AUTHORS.rst": false,
        "CHANGELOG.md": false,
        "CHANGELOG.rst": false,
        "CONTRIBUTING.md": false,
        "CONTRIBUTING.rst": false,
        "LICENSE": true,
        "LICENSE.txt": false,
        "MANIFEST.in": true,
        "Makefile": true,
        "README": false,
        "README.md": false,
        "README.rst": true,
        "pytest.ini": false,
        "requirements.txt": false,
        "setup.cfg": true,
        "setup.py": true,
        "test-requirements.txt": false,
        "tox.ini": false
    },
    "license": "MIT",
    "lines_of_code": {
        "": 1,
        "bat": 36,
        "c": 22747,
        "cfg": 98,
        "h": 1136,
        "html": 162,
        "in": 1,
        "lock": 82,
        "md": 3,
        "pem": 5616,
        "ps1": 229,
        "py": 154096,
        "rst": 1372,
        "sample": 640,
        "sh": 5,
        "txt": 505,
        "yml": 80
    },
    "pep8_infringement": 87863,
    "requirements": [
        "pew>=0.1.26",
        "pip>=9.0.1",
        "pip-tools>=1.9.0",
        "requests>2.0.0",
        "virtualenv"
    ],
    "shebang": {
        "#!/usr/bin/env python": 13
    }
}