{
    "has_dir": {
        "doc/": false,
        "docs/": false,
        "examples/": false,
        "src/": false,
        "test/": false,
        "tests/": true
    },
    "has_file": {
        ".gitignore": true,
        "AUTHORS.md": false,
        "AUTHORS.rst": false,
        "CHANGELOG.md": false,
        "CHANGELOG.rst": false,
        "CONTRIBUTING.md": false,
        "CONTRIBUTING.rst": false,
        "LICENSE": true,
        "LICENSE.txt": false,
        "MANIFEST.in": true,
        "Makefile": true,
        "README": false,
        "README.md": false,
        "README.rst": true,
        "pytest.ini": false,
        "requirements.txt": false,
        "setup.cfg": true,
        "setup.py": true,
        "test-requirements.txt": true,
        "tox.ini": true
    },
    "install_requires": [
        "requests"
    ],
    "license": "BSD-2-Clause",
    "lines_of_code": {
        "cfg": 9,
        "in": 0,
        "ini": 11,
        "py": 1005,
        "rst": 216,
        "txt": 6,
        "xml": 17773
    },
    "pep8_infringement": 19,
    "shebang": {
        "#!/usr/bin/env python": 6
    }
}