{
    "has_dir": {
        "doc/": false,
        "docs/": true,
        "examples/": false,
        "src/": false,
        "test/": false,
        "tests/": true
    },
    "has_file": {
        ".gitignore": true,
        "AUTHORS.md": false,
        "AUTHORS.rst": false,
        "CHANGELOG.md": false,
        "CHANGELOG.rst": false,
        "CONTRIBUTING.md": false,
        "CONTRIBUTING.rst": false,
        "LICENSE": true,
        "LICENSE.txt": false,
        "MANIFEST.in": true,
        "Makefile": false,
        "README": true,
        "README.md": false,
        "README.rst": false,
        "pytest.ini": true,
        "requirements.txt": false,
        "setup.cfg": true,
        "setup.py": true,
        "test-requirements.txt": false,
        "tox.ini": false
    },
    "install_requires": [],
    "license": "GPL-3.0",
    "lines_of_code": {
        "cfg": 3,
        "in": 1,
        "ini": 2,
        "py": 563,
        "rst": 38
    },
    "pep8_infringement": 49,
    "shebang": {
        "#!/usr/bin/env python3": 1
    }
}