{
    "has_dir": {
        "doc/": false,
        "docs/": true,
        "examples/": false,
        "src/": false,
        "test/": true,
        "tests/": false
    },
    "has_file": {
        ".gitignore": true,
        "AUTHORS.md": false,
        "AUTHORS.rst": false,
        "CHANGELOG.md": false,
        "CHANGELOG.rst": false,
        "CONTRIBUTING.md": false,
        "CONTRIBUTING.rst": true,
        "LICENSE": false,
        "LICENSE.txt": false,
        "MANIFEST.in": true,
        "Makefile": false,
        "README": false,
        "README.md": false,
        "README.rst": true,
        "pytest.ini": false,
        "requirements.txt": true,
        "setup.cfg": false,
        "setup.py": true,
        "test-requirements.txt": false,
        "tox.ini": false
    },
    "license": null,
    "lines_of_code": {
        "": 1,
        "bat": 36,
        "css": 17,
        "html": 35,
        "in": 3,
        "php": 134,
        "py": 3667,
        "rst": 1017,
        "sample": 640,
        "svg": 38,
        "txt": 6,
        "yml": 25
    },
    "pep8_infringement": 548,
    "requirements": [
        "beautifulsoup4==4.5.3",
        "lxml==3.7.3",
        "requests==2.13.0",
        "sphinx==1.5.5",
        "sphinx-better-theme==0.13",
        "sphinxcontrib-napoleon==0.6.1"
    ],
    "shebang": {
        "#!/usr/bin/env python3": 1
    }
}