{
    "has_dir": {
        "doc/": true,
        "docs/": false,
        "examples/": true,
        "src/": false,
        "test/": false,
        "tests/": true
    },
    "has_file": {
        ".gitignore": true,
        "AUTHORS.md": false,
        "AUTHORS.rst": false,
        "CHANGELOG.md": false,
        "CHANGELOG.rst": false,
        "CONTRIBUTING.md": false,
        "CONTRIBUTING.rst": false,
        "LICENSE": true,
        "LICENSE.txt": false,
        "MANIFEST.in": false,
        "Makefile": true,
        "README": false,
        "README.md": true,
        "README.rst": false,
        "pytest.ini": false,
        "requirements.txt": false,
        "setup.cfg": true,
        "setup.py": true,
        "test-requirements.txt": false,
        "tox.ini": false
    },
    "license": "Apache-2.0",
    "lines_of_code": {
        "": 8,
        "c": 50929,
        "cfg": 2,
        "ipynb": 1360,
        "md": 182,
        "py": 3235,
        "rst": 1095,
        "sample": 640,
        "template": 1343,
        "txt": 5,
        "yml": 58
    },
    "pep8_infringement": 174,
    "requirements": [
        "numpy",
        "requests",
        "scipy>=0.17.0"
    ],
    "shebang": {}
}