{
    "has_dir": {
        "doc/": true,
        "docs/": false,
        "examples/": true,
        "src/": false,
        "test/": false,
        "tests/": true
    },
    "has_file": {
        ".gitignore": true,
        "AUTHORS.md": false,
        "AUTHORS.rst": false,
        "CHANGELOG.md": false,
        "CHANGELOG.rst": false,
        "CONTRIBUTING.md": false,
        "CONTRIBUTING.rst": false,
        "LICENSE": false,
        "LICENSE.txt": true,
        "MANIFEST.in": true,
        "Makefile": false,
        "README": false,
        "README.md": false,
        "README.rst": false,
        "pytest.ini": false,
        "requirements.txt": false,
        "setup.cfg": false,
        "setup.py": true,
        "test-requirements.txt": false,
        "tox.ini": false
    },
    "license": "BSD-3-Clause",
    "lines_of_code": {
        "bat": 170,
        "com": 1437,
        "css": 189,
        "dat": 11,
        "in": 72,
        "out": 17,
        "py": 30668,
        "rst": 2567,
        "sample": 640,
        "txt": 406
    },
    "pep8_infringement": 1623,
    "requirements": [
        "numpy",
        "scipy"
    ],
    "shebang": {
        "#! /usr/bin/env python": 93,
        "#!/usr/bin/env python": 3
    }
}