{
    "has_dir": {
        "doc/": false,
        "docs/": false,
        "examples/": false,
        "src/": false,
        "test/": false,
        "tests/": false
    },
    "has_file": {
        ".gitignore": true,
        "AUTHORS.md": false,
        "AUTHORS.rst": false,
        "CHANGELOG.md": false,
        "CHANGELOG.rst": false,
        "CONTRIBUTING.md": false,
        "CONTRIBUTING.rst": false,
        "LICENSE": true,
        "LICENSE.txt": false,
        "MANIFEST.in": false,
        "Makefile": false,
        "README": false,
        "README.md": true,
        "README.rst": false,
        "pytest.ini": false,
        "requirements.txt": false,
        "setup.cfg": false,
        "setup.py": false,
        "test-requirements.txt": false,
        "tox.ini": false
    },
    "requirements": [],
    "license": "AGPL-3.0",
    "lines_of_code": {
        "csv": 10,
        "html": 171,
        "md": 72,
        "po": 2565,
        "pot": 3242,
        "py": 9123,
        "rst": 665,
        "svg": 98,
        "txt": 7,
        "xml": 3728,
        "yml": 744
    },
    "pep8_infringement": 0,
    "shebang": {}
}