{
    "has_dir": {
        "doc/": false,
        "docs/": true,
        "examples/": true,
        "src/": false,
        "test/": true,
        "tests/": false
    },
    "has_file": {
        ".gitignore": true,
        "AUTHORS.md": false,
        "AUTHORS.rst": false,
        "CHANGELOG.md": false,
        "CHANGELOG.rst": false,
        "CONTRIBUTING.md": false,
        "CONTRIBUTING.rst": false,
        "LICENSE": true,
        "LICENSE.txt": false,
        "MANIFEST.in": true,
        "Makefile": true,
        "README": false,
        "README.md": false,
        "README.rst": true,
        "pytest.ini": false,
        "requirements.txt": true,
        "setup.cfg": false,
        "setup.py": true,
        "test-requirements.txt": false,
        "tox.ini": true
    },
    "license": "MIT",
    "lines_of_code": {
        "asc": 157,
        "conf": 52,
        "css": 387,
        "css_t": 620,
        "html": 140,
        "in": 25,
        "ini": 80,
        "py": 13555,
        "rst": 1864,
        "sample": 640,
        "sh": 30,
        "svg": 946,
        "tac": 51,
        "txt": 32,
        "yml": 11
    },
    "pep8_infringement": 417,
    "requirements": [
        "ipaddr>=2.1.10",
        "twisted>=11.1.0",
        "zope.interface>=3.6.1"
    ],
    "shebang": {
        "#!/usr/bin/env python": 22
    }
}